<?xml version="1.0" encoding="utf-8"?>
<!DOCTYPE hibernate-mapping PUBLIC "-//Hibernate/Hibernate Mapping DTD 3.0//EN"
"http://www.hibernate.org/dtd/hibernate-mapping-3.0.dtd">
<!-- 
    Mapping file autogenerated by MyEclipse Persistence Tools
-->

<hibernate-mapping>

    <class name="cn.zqrc.ftms.pro.vo.Bid" table="bid" catalog="trade">
        <id name="id" type="java.lang.Integer">
            <column name="bid_id" />
            <generator class="native"></generator>
        </id>
        <many-to-one name="project" lazy="false" class="cn.zqrc.ftms.pro.vo.Project" fetch="select">
            <column name="bid_project" />
        </many-to-one>
        <property name="user" type="java.lang.String">
            <column name="bid_user" length="32" />
        </property>
        <property name="beginTime" type="java.util.Date">
            <column name="bid_beginTime" length="0" />
        </property>
        <property name="bidTime" type="java.util.Date">
            <column name="bid_bidTime" length="0" />
        </property>
        <property name="elec" type="java.lang.String">
            <column name="bid_elec" length="32" />
        </property>
        <property name="info" type="java.lang.String">
            <column name="bid_info" />
        </property>
        <property name="result" type="java.lang.String">
            <column name="bid_result" />
        </property>
        <property name="notice" type="java.lang.String">
            <column name="bid_notice" />
        </property>
        <property name="elecFile" type="java.lang.String">
            <column name="bid_elecFile" />
        </property>
    </class>
</hibernate-mapping>
